uqpylab/__init__.py
uqpylab/display_general.py
uqpylab/display_inversion.py
uqpylab/display_reliability.py
uqpylab/display_sensitivity.py
uqpylab/display_util.py
uqpylab/helpers.py
uqpylab/interface.py
uqpylab/sessions.py
uqpylab/test/LOCAL_test_sessions.py
uqpylab/test/__init__.py
uqpylab/test/conftest.py
uqpylab/test/local_mat_debug.py
uqpylab/test/pck_FullInput.py
uqpylab/test/pck_display_debug.py
uqpylab/test/quickTest.py
uqpylab/test/quickTest_sens.py
uqpylab/test/suppress_jupyter_warnings.sh
uqpylab/test/test_analysis.py
uqpylab/test/test_display.py
uqpylab/test/test_inference.py
uqpylab/test/test_input.py
uqpylab/test/test_input_aux_funs.py
uqpylab/test/test_intermids.py
uqpylab/test/test_inversion.py
uqpylab/test/test_mat_input.py
uqpylab/test/test_mat_model.py
uqpylab/test/test_model.py
uqpylab/test/test_sessions.py
uqpylab/test/test_singleton.py
uqpylab/test/true_models.py
uqpylab-1.2.dist-info/LICENSE
uqpylab-1.2.dist-info/METADATA
uqpylab-1.2.dist-info/WHEEL
uqpylab-1.2.dist-info/RECORD
