Metadata-Version: 2.1
Name: uqpylab
Version: 1.2
Summary: Official UQCloud python client: cloud-based uncertainty quantification in python with UQLab.
License: BSD
Author: C. Lataniotis
Requires-Python: >=3.9
Classifier: License :: Other/Proprietary License
Classifier: Programming Language :: Python :: 3
Classifier: Programming Language :: Python :: 3.9
Classifier: Programming Language :: Python :: 3.10
Classifier: Programming Language :: Python :: 3.11
Classifier: Programming Language :: Python :: 3.12
Requires-Dist: appdirs (>=1.4.4)
Requires-Dist: ipython (>=8.7.0)
Requires-Dist: ipywidgets (>=8.0.4)
Requires-Dist: matplotlib (>=3.5.2)
Requires-Dist: numpy (>=1.21.6,<2)
Requires-Dist: pandas (>=1.3.5)
Requires-Dist: plotly (>=5.11.0)
Requires-Dist: requests (>=2.28.2)
Requires-Dist: scipy (>=1.10.0)
